tf_lazy_loader/__init__.py
tf_lazy_loader-0.1.1.dist-info/LICENSE
tf_lazy_loader-0.1.1.dist-info/METADATA
tf_lazy_loader-0.1.1.dist-info/WHEEL
tf_lazy_loader-0.1.1.dist-info/RECORD
