Metadata-Version: 2.1
Name: tf-lazy-loader
Version: 0.1.1
Summary: Lazy loading of Python modules, based on TensorFlow's LazyLoader util.
Author: Nathan Jones
Author-email: purkinje90@gmail.com
Requires-Python: >=3.10,<4.0
Classifier: Programming Language :: Python :: 3
Classifier: Programming Language :: Python :: 3.10
Classifier: Programming Language :: Python :: 3.11
Classifier: Programming Language :: Python :: 3.12
